gemdat/__init__.py
gemdat/_plot_backend.py
gemdat/caching.py
gemdat/collective.py
gemdat/io.py
gemdat/jumps.py
gemdat/metrics.py
gemdat/orientations.py
gemdat/path.py
gemdat/rdf.py
gemdat/segmentation.py
gemdat/shape.py
gemdat/trajectory.py
gemdat/transitions.py
gemdat/utils.py
gemdat/volume.py
gemdat/data/argyrodite.cif
gemdat/data/lagp.cif
gemdat/data/latp.cif
gemdat/data/li3ps4.cif
gemdat/data/lisnps.cif
gemdat/data/logo.png
gemdat/data/logo_on_black.png
gemdat/data/logo_on_white.png
gemdat/data/mno2_lambda.cif
gemdat/data/na3ps4.cif
gemdat/plots/__init__.py
gemdat/plots/_shared.py
gemdat/plots/matplotlib/__init__.py
gemdat/plots/matplotlib/_autocorrelation.py
gemdat/plots/matplotlib/_bond_length_distribution.py
gemdat/plots/matplotlib/_collective_jumps.py
gemdat/plots/matplotlib/_displacement_histogram.py
gemdat/plots/matplotlib/_displacement_per_atom.py
gemdat/plots/matplotlib/_displacement_per_element.py
gemdat/plots/matplotlib/_energy_along_path.py
gemdat/plots/matplotlib/_frequency_vs_occurence.py
gemdat/plots/matplotlib/_jumps_3d.py
gemdat/plots/matplotlib/_jumps_3d_animation.py
gemdat/plots/matplotlib/_jumps_vs_distance.py
gemdat/plots/matplotlib/_jumps_vs_time.py
gemdat/plots/matplotlib/_msd_per_element.py
gemdat/plots/matplotlib/_polar.py
gemdat/plots/matplotlib/_radial_distribution.py
gemdat/plots/matplotlib/_rectilinear.py
gemdat/plots/matplotlib/_shape.py
gemdat/plots/matplotlib/_vibrational_amplitudes.py
gemdat/plots/plotly/__init__.py
gemdat/plots/plotly/_autocorrelation.py
gemdat/plots/plotly/_bond_length_distribution.py
gemdat/plots/plotly/_collective_jumps.py
gemdat/plots/plotly/_density.py
gemdat/plots/plotly/_displacement_histogram.py
gemdat/plots/plotly/_displacement_per_atom.py
gemdat/plots/plotly/_displacement_per_element.py
gemdat/plots/plotly/_energy_along_path.py
gemdat/plots/plotly/_frequency_vs_occurence.py
gemdat/plots/plotly/_jumps_3d.py
gemdat/plots/plotly/_jumps_vs_distance.py
gemdat/plots/plotly/_jumps_vs_time.py
gemdat-1.6.2.dist-info/licenses/LICENSE
gemdat-1.6.2.dist-info/METADATA
gemdat-1.6.2.dist-info/WHEEL
gemdat-1.6.2.dist-info/top_level.txt
gemdat-1.6.2.dist-info/RECORD
