Metadata-Version: 2.4
Name: GEMDAT
Version: 1.6.2
Summary: Generalized Molecular Dynamics Analysis Tool
Author-email: Victor Azizi <v.azizi@esciencecenter.nl>, Stef Smeets <s.smeets@esciencecenter.nl>
License: Apache 2.0 License
Project-URL: homepage, https://github.com/GEMDAT-repos/GEMDAT
Project-URL: issues, https://github.com/GEMDAT-repos/GEMDAT/issues
Project-URL: documentation, https://gemdat.readthedocs.io
Project-URL: changelog, https://github.com/GEMDAT-repos/GEMDAT/releases
Keywords: analysis,molecular dynamics,diffusion,batteries
Classifier: Development Status :: 5 - Production/Stable
Classifier: Intended Audience :: Science/Research
Classifier: License :: OSI Approved :: Apache Software License
Classifier: Natural Language :: English
Classifier: Operating System :: OS Independent
Classifier: Programming Language :: Python :: 3
Classifier: Programming Language :: Python :: 3.10
Classifier: Programming Language :: Python :: 3.11
Classifier: Programming Language :: Python :: 3.12
Classifier: Topic :: Scientific/Engineering
Requires-Python: >=3.10
License-File: LICENSE
Requires-Dist: matplotlib>=3.6.0
Requires-Dist: MDAnalysis
Requires-Dist: numpy
Requires-Dist: pymatgen!=2024.2.20,>=2024.1.26
Requires-Dist: rich
Requires-Dist: scikit-image
Requires-Dist: scipy
Provides-Extra: develop
Requires-Dist: kaleido<0.4; extra == "develop"
Requires-Dist: bump-my-version; extra == "develop"
Requires-Dist: coverage[toml]; extra == "develop"
Requires-Dist: mypy; extra == "develop"
Requires-Dist: pre-commit; extra == "develop"
Requires-Dist: pytest>=8.1; extra == "develop"
Provides-Extra: docs
Requires-Dist: markdown-include; extra == "docs"
Requires-Dist: mkdocs; extra == "docs"
Requires-Dist: mkdocs-jupyter; extra == "docs"
Requires-Dist: mkdocs-material; extra == "docs"
Requires-Dist: mkdocstrings[python]; extra == "docs"
Provides-Extra: publishing
Requires-Dist: twine; extra == "publishing"
Requires-Dist: wheel; extra == "publishing"
Requires-Dist: build; extra == "publishing"
Dynamic: license-file
